{
  "version": 3,
  "middleware": {
    "/": {
      "files": [
        "server/edge-runtime-webpack.js",
        "server/src/middleware.js"
      ],
      "name": "src/middleware",
      "page": "/",
      "matchers": [
        {
          "regexp": "^(?:\\/(_next\\/data\\/[^/]{1,}))?(?:\\/((?!api|_next|.*\\..*).*))(\\.json)?[\\/#\\?]?$",
          "originalSource": "/((?!api|_next|.*\\..*).*)"
        },
        {
          "regexp": "^(?:\\/(_next\\/data\\/[^/]{1,}))?(?:\\/(\\/?index|\\/?index\\.json))?[\\/#\\?]?$",
          "originalSource": "/"
        }
      ],
      "wasm": [],
      "assets": [],
      "env": {
        "__NEXT_BUILD_ID": "w1BvEqlJyApfxa4F200Dn",
        "NEXT_SERVER_ACTIONS_ENCRYPTION_KEY": "QCVip9UjVJgtWNKZ+ytC5d4y7NPk4RREnKSskH5W2R4=",
        "__NEXT_PREVIEW_MODE_ID": "ef13cc3eb8ac828e0cb82d75da64e79d",
        "__NEXT_PREVIEW_MODE_ENCRYPTION_KEY": "6ef5bff13c88029e5067b73ec5043a1b699a98768af66ebbf175248d5c670265",
        "__NEXT_PREVIEW_MODE_SIGNING_KEY": "f9f349b9f5e98bf5023b2cb1c4b34cb0ca10235dc49cc80982a0e01d5732bd20"
      }
    }
  },
  "functions": {},
  "sortedMiddleware": [
    "/"
  ]
}