{
	"version": "2.0.0",
	"tasks": [
		{
			"label": "SSH to FengShui Server",
			"type": "shell",
			"command": "ssh",
			"args": ["fengshui"],
			"group": "build",
			"presentation": {
				"echo": true,
				"reveal": "always",
				"focus": false,
				"panel": "new",
				"showReuseMessage": true,
				"clear": false
			},
			"problemMatcher": []
		},
		{
			"label": "SSH to FengShui (Short)",
			"type": "shell",
			"command": "ssh",
			"args": ["fs"],
			"group": "build",
			"presentation": {
				"echo": true,
				"reveal": "always",
				"focus": false,
				"panel": "new"
			},
			"problemMatcher": []
		}
	]
}
